unitycatalog/ai/litellm/__init__.py
unitycatalog/ai/litellm/toolkit.py
unitycatalog/ai/litellm/utils.py
unitycatalog/ai/litellm/version.py
unitycatalog_litellm-0.2.0.dist-info/METADATA
unitycatalog_litellm-0.2.0.dist-info/WHEEL
unitycatalog_litellm-0.2.0.dist-info/RECORD
