Metadata-Version: 2.4
Name: unitycatalog-litellm
Version: 0.2.0
Summary: Support for Unity Catalog functions as LiteLLM tools
Author-email: Michael Berk <michael.berk@databricks.com>
License: Apache-2.0
Requires-Python: >=3.9
Requires-Dist: litellm>=1.50.1
Requires-Dist: unitycatalog-ai
Provides-Extra: databricks-dev
Requires-Dist: unitycatalog-ai[databricks-dev]; extra == 'databricks-dev'
Provides-Extra: dev
Requires-Dist: unitycatalog-ai[dev]; extra == 'dev'
